1_bit_ALU/onebitalu.v
/*
The following is the verilog code for a 1 bit ALU that can perform the following logical and arithmetic operations - AND,OR,NOR,NAND,ADD and SUBTRACT. There are 2 additional flags - zero and a flag to check whether the first input is greater than the second input.
*/

module fullbitadder(input A,input B,input carryin,output sum,output carryout); 

 assign sum = (A ^ B ^ carryin);
 assign carryout = ((A ^ B) & carryin)|(A & B);

endmodule

module mux2input(input x,input y,input signal,output OUTPUT);

 assign OUTPUT = (x & ~signal)|(y & signal);

endmodule

module mux3input(input x1,input x2,input x3,input [1:0]signal,output OUTPUT);

 assign OUTPUT = (~signal[0] & ~signal[1] & x1)|(signal[0] & ~signal[1] & x2)|(~signal[0] & signal[1] & x3); 

endmodule
 
module onebitalu(input a,input b,input ainv,input binv,input carryin,input [1:0]operation,output carryout,output result,output zero,output sgt);

 wire A;
 wire B;
 wire sum; // This wire carries (a+b) when ainv = 0,binv = 0 and carryin = 0. The wire carries (a-b) when ainv = 0, binv = 1 and carryin = 1
 wire a_and_b; // This wire carries value (a and b) when ainv = 0 and binv = 0. The wire carries (a nor b) when ainv = 1 and binv = 1
 wire a_or_b;  // This wire carries value (a or b) when ainv = 0 and binv = 0. The wire carries (a nand b) when ainv = 1 and binv = 1
 
 
 fullbitadder f(A,B,carryin,sum,carryout);  //1 bit adder to compute a+b or a-b
 
 mux2input m1(a,~a,ainv,A);  //Output of this 2 to 1 mux depends on ainv signal 
 mux2input m2(b,~b,binv,B);  //Output of this 2 to 1 mux depends on binv signal
 
 mux3input M(a_and_b,a_or_b,sum,operation,result);
 
 assign zero = ~result;     //Zero flag
 assign sgt = (a & ~b);     //Set greater than flag : When a = 1 and b = 0,its output is 1
 assign a_and_b = A & B;    
 assign a_or_b = A | B;

endmodule

module stimulus;

 reg a;
 reg b;
 reg ainv;
 reg binv;
 reg carryin;
 wire carryout;
 reg [1:0]operation;  
 wire zero;
 wire result;
 wire sgt;
 
 /*
 
 Input code
 
 ainv  binv  carryin operation   
 
  0     0      X        00     -- AND  
  0     0      X        01     -- OR
  1     1      X        00     -- NOR
  1     1      X        01     -- NAND
  0     0      0        00     -- ADD
  0     1      1        00     -- SUBTRACT
  
  */
  
 
 onebitalu uut(a,b,ainv,binv,carryin,operation,carryout,result,zero,sgt);
 
 initial begin
 
 $dumpfile("onebitalu.vcd");
 $dumpvars(0,stimulus);
 
 $display("A  B  Ainvert  Binvert  Carry_In  Operation  Carry_Out  Result  Zero  Set_greater_than\n");
 
 #0 a=0;b=0;ainv=0;binv=0;carryin=0;operation=0;
 #10 a=0;b=1;ainv=0;binv=0;carryin=0;operation=1;
 #10 a=0;b=1;ainv=0;binv=0;carryin=0;operation=2;
 #10 a=1;b=1;ainv=0;binv=1;carryin=1;operation=2;
 #10 a=1;b=0;ainv=0;binv=1;carryin=1;operation=2;
 #10 a=1;b=1;ainv=0;binv=0;carryin=0;operation=2;
 #10 a=1;b=1;ainv=0;binv=0;carryin=0;operation=0;
 #10 a=0;b=1;ainv=1;binv=1;carryin=0;operation=1;
 #10 a=0;b=0;ainv=1;binv=1;carryin=0;operation=0;
 #10 a=1;b=1;ainv=0;binv=0;carryin=0;operation=2;
 #10 a=1;b=1;ainv=0;binv=1;carryin=1;operation=2;
 #10 a=1;b=0;ainv=0;binv=1;carryin=1;operation=2;
 #10;
 
 end
 
 initial begin
 
   $monitor("%d  %d     %d        %d        %d         %2b          %d        %d      %d          %d",a,b,ainv,binv,carryin,operation,carryout,result,zero,sgt);
   
 end
 
endmodule

1_bit_ALU/onebitalu.vcd
$date
	Mon Oct 30 22:27:56 2017
$end
$version
	Icarus Verilog
$end
$timescale
	1s
$end
$scope module stimulus $end
$var wire 1 ! carryout $end
$var wire 1 " result $end
$var wire 1 # sgt $end
$var wire 1 $ zero $end
$var reg 1 % a $end
$var reg 1 & ainv $end
$var reg 1 ' b $end
$var reg 1 ( binv $end
$var reg 1 ) carryin $end
$var reg 2 * operation [1:0] $end
$scope module uut $end
$var wire 1 + A $end
$var wire 1 , B $end
$var wire 1 - a $end
$var wire 1 . a_and_b $end
$var wire 1 / a_or_b $end
$var wire 1 0 ainv $end
$var wire 1 1 b $end
$var wire 1 2 binv $end
$var wire 1 3 carryin $end
$var wire 1 ! carryout $end
$var wire 2 4 operation [1:0] $end
$var wire 1 " result $end
$var wire 1 # sgt $end
$var wire 1 5 sum $end
$var wire 1 $ zero $end
$scope module f $end
$var wire 1 + A $end
$var wire 1 , B $end
$var wire 1 3 carryin $end
$var wire 1 ! carryout $end
$var wire 1 5 sum $end
$upscope $end
$scope module m1 $end
$var wire 1 + OUTPUT $end
$var wire 1 0 signal $end
$var wire 1 - x $end
$var wire 1 6 y $end
$upscope $end
$scope module m2 $end
$var wire 1 , OUTPUT $end
$var wire 1 2 signal $end
$var wire 1 1 x $end
$var wire 1 7 y $end
$upscope $end
$scope module M $end
$var wire 1 " OUTPUT $end
$var wire 2 8 signal [1:0] $end
$var wire 1 . x1 $end
$var wire 1 / x2 $end
$var wire 1 5 x3 $end
$upscope $end
$upscope $end
$upscope $end
$enddefinitions $end
#0
$dumpvars
b0 8
17
16
05
b0 4
03
02
01
00
0/
0.
0-
0,
0+
b0 *
0)
0(
0'
0&
0%
1$
0#
0"
0!
$end
#10
0$
1"
15
1/
1,
07
b1 *
b1 4
b1 8
1'
11
#20
b10 *
b10 4
b10 8
#30
1$
0"
0,
0.
1!
1+
05
06
1)
13
1(
12
1%
1-
#40
0$
1"
15
1.
1,
1#
17
0'
01
#50
1$
1!
0"
1.
1,
0#
05
07
0)
03
0(
02
1'
11
#60
0$
1"
b0 *
b0 4
b0 8
#70
0!
15
0.
0,
16
b1 *
b1 4
b1 8
1(
12
1&
10
0%
0-
#80
0$
1"
1!
05
1.
1,
17
b0 *
b0 4
b0 8
0'
01
#90
1$
0"
1!
1/
1.
1,
1+
07
06
0#
b10 *
b10 4
b10 8
0(
02
0&
00
1'
11
1%
1-
#100
1$
0.
0"
0,
05
1)
13
1(
12
#110
0$
1"
15
1.
1,
1#
17
0'
01
